[
  {
    "date": "2026-03-08",
    "btc_pred": 67696.04,
    "eth_pred": 1971.22
  },
  {
    "date": "2026-03-09",
    "btc_pred": 67575.45,
    "eth_pred": 1969.44
  },
  {
    "date": "2026-03-10",
    "btc_pred": 67454.86,
    "eth_pred": 1967.66
  },
  {
    "date": "2026-03-11",
    "btc_pred": 67334.27,
    "eth_pred": 1965.88
  },
  {
    "date": "2026-03-12",
    "btc_pred": 67213.67,
    "eth_pred": 1964.1
  },
  {
    "date": "2026-03-13",
    "btc_pred": 67093.08,
    "eth_pred": 1962.31
  },
  {
    "date": "2026-03-14",
    "btc_pred": 66972.49,
    "eth_pred": 1960.53
  },
  {
    "date": "2026-03-15",
    "btc_pred": 66851.9,
    "eth_pred": 1958.75
  },
  {
    "date": "2026-03-16",
    "btc_pred": 66731.31,
    "eth_pred": 1956.97
  },
  {
    "date": "2026-03-17",
    "btc_pred": 66610.72,
    "eth_pred": 1955.19
  },
  {
    "date": "2026-03-18",
    "btc_pred": 66490.13,
    "eth_pred": 1953.41
  },
  {
    "date": "2026-03-19",
    "btc_pred": 66369.53,
    "eth_pred": 1951.63
  },
  {
    "date": "2026-03-20",
    "btc_pred": 66248.94,
    "eth_pred": 1949.84
  },
  {
    "date": "2026-03-21",
    "btc_pred": 66128.35,
    "eth_pred": 1948.06
  },
  {
    "date": "2026-03-22",
    "btc_pred": 66007.76,
    "eth_pred": 1946.28
  },
  {
    "date": "2026-03-23",
    "btc_pred": 65887.17,
    "eth_pred": 1944.5
  },
  {
    "date": "2026-03-24",
    "btc_pred": 65766.58,
    "eth_pred": 1942.72
  },
  {
    "date": "2026-03-25",
    "btc_pred": 65645.99,
    "eth_pred": 1940.94
  },
  {
    "date": "2026-03-26",
    "btc_pred": 65525.39,
    "eth_pred": 1939.15
  },
  {
    "date": "2026-03-27",
    "btc_pred": 65404.8,
    "eth_pred": 1937.37
  },
  {
    "date": "2026-03-28",
    "btc_pred": 65284.21,
    "eth_pred": 1935.59
  },
  {
    "date": "2026-03-29",
    "btc_pred": 65163.62,
    "eth_pred": 1933.81
  },
  {
    "date": "2026-03-30",
    "btc_pred": 65043.03,
    "eth_pred": 1932.03
  },
  {
    "date": "2026-03-31",
    "btc_pred": 64922.44,
    "eth_pred": 1930.25
  },
  {
    "date": "2026-04-01",
    "btc_pred": 64801.85,
    "eth_pred": 1928.47
  },
  {
    "date": "2026-04-02",
    "btc_pred": 64681.25,
    "eth_pred": 1926.68
  },
  {
    "date": "2026-04-03",
    "btc_pred": 64560.66,
    "eth_pred": 1924.9
  },
  {
    "date": "2026-04-04",
    "btc_pred": 64440.07,
    "eth_pred": 1923.12
  },
  {
    "date": "2026-04-05",
    "btc_pred": 64319.48,
    "eth_pred": 1921.34
  },
  {
    "date": "2026-04-06",
    "btc_pred": 64198.89,
    "eth_pred": 1919.56
  }
]