[
  {
    "date": "2026-06-27",
    "btc_pred": 59821.78,
    "eth_pred": 1551.89
  },
  {
    "date": "2026-06-28",
    "btc_pred": 59659.12,
    "eth_pred": 1542.51
  },
  {
    "date": "2026-06-29",
    "btc_pred": 59496.46,
    "eth_pred": 1533.14
  },
  {
    "date": "2026-06-30",
    "btc_pred": 59333.8,
    "eth_pred": 1523.77
  },
  {
    "date": "2026-07-01",
    "btc_pred": 59171.14,
    "eth_pred": 1514.39
  },
  {
    "date": "2026-07-02",
    "btc_pred": 59008.49,
    "eth_pred": 1505.02
  },
  {
    "date": "2026-07-03",
    "btc_pred": 58845.83,
    "eth_pred": 1495.65
  },
  {
    "date": "2026-07-04",
    "btc_pred": 58683.17,
    "eth_pred": 1486.27
  },
  {
    "date": "2026-07-05",
    "btc_pred": 58520.51,
    "eth_pred": 1476.9
  },
  {
    "date": "2026-07-06",
    "btc_pred": 58357.85,
    "eth_pred": 1467.53
  },
  {
    "date": "2026-07-07",
    "btc_pred": 58195.19,
    "eth_pred": 1458.15
  },
  {
    "date": "2026-07-08",
    "btc_pred": 58032.54,
    "eth_pred": 1448.78
  },
  {
    "date": "2026-07-09",
    "btc_pred": 57869.88,
    "eth_pred": 1439.4
  },
  {
    "date": "2026-07-10",
    "btc_pred": 57707.22,
    "eth_pred": 1430.03
  },
  {
    "date": "2026-07-11",
    "btc_pred": 57544.56,
    "eth_pred": 1420.66
  },
  {
    "date": "2026-07-12",
    "btc_pred": 57381.9,
    "eth_pred": 1411.28
  },
  {
    "date": "2026-07-13",
    "btc_pred": 57219.24,
    "eth_pred": 1401.91
  },
  {
    "date": "2026-07-14",
    "btc_pred": 57056.59,
    "eth_pred": 1392.54
  },
  {
    "date": "2026-07-15",
    "btc_pred": 56893.93,
    "eth_pred": 1383.16
  },
  {
    "date": "2026-07-16",
    "btc_pred": 56731.27,
    "eth_pred": 1373.79
  },
  {
    "date": "2026-07-17",
    "btc_pred": 56568.61,
    "eth_pred": 1364.41
  },
  {
    "date": "2026-07-18",
    "btc_pred": 56405.95,
    "eth_pred": 1355.04
  },
  {
    "date": "2026-07-19",
    "btc_pred": 56243.29,
    "eth_pred": 1345.67
  },
  {
    "date": "2026-07-20",
    "btc_pred": 56080.63,
    "eth_pred": 1336.29
  },
  {
    "date": "2026-07-21",
    "btc_pred": 55917.98,
    "eth_pred": 1326.92
  },
  {
    "date": "2026-07-22",
    "btc_pred": 55755.32,
    "eth_pred": 1317.55
  },
  {
    "date": "2026-07-23",
    "btc_pred": 55592.66,
    "eth_pred": 1308.17
  },
  {
    "date": "2026-07-24",
    "btc_pred": 55430.0,
    "eth_pred": 1298.8
  },
  {
    "date": "2026-07-25",
    "btc_pred": 55267.34,
    "eth_pred": 1289.43
  },
  {
    "date": "2026-07-26",
    "btc_pred": 55104.68,
    "eth_pred": 1280.05
  }
]