[
  {
    "date": "2026-02-21",
    "btc_pred": 67695.93,
    "eth_pred": 1959.96
  },
  {
    "date": "2026-02-22",
    "btc_pred": 67606.4,
    "eth_pred": 1960.42
  },
  {
    "date": "2026-02-23",
    "btc_pred": 67516.87,
    "eth_pred": 1960.88
  },
  {
    "date": "2026-02-24",
    "btc_pred": 67427.34,
    "eth_pred": 1961.34
  },
  {
    "date": "2026-02-25",
    "btc_pred": 67337.81,
    "eth_pred": 1961.8
  },
  {
    "date": "2026-02-26",
    "btc_pred": 67248.28,
    "eth_pred": 1962.26
  },
  {
    "date": "2026-02-27",
    "btc_pred": 67158.75,
    "eth_pred": 1962.72
  },
  {
    "date": "2026-02-28",
    "btc_pred": 67069.23,
    "eth_pred": 1963.18
  },
  {
    "date": "2026-03-01",
    "btc_pred": 66979.7,
    "eth_pred": 1963.64
  },
  {
    "date": "2026-03-02",
    "btc_pred": 66890.17,
    "eth_pred": 1964.1
  },
  {
    "date": "2026-03-03",
    "btc_pred": 66800.64,
    "eth_pred": 1964.56
  },
  {
    "date": "2026-03-04",
    "btc_pred": 66711.11,
    "eth_pred": 1965.02
  },
  {
    "date": "2026-03-05",
    "btc_pred": 66621.58,
    "eth_pred": 1965.49
  },
  {
    "date": "2026-03-06",
    "btc_pred": 66532.05,
    "eth_pred": 1965.95
  },
  {
    "date": "2026-03-07",
    "btc_pred": 66442.53,
    "eth_pred": 1966.41
  },
  {
    "date": "2026-03-08",
    "btc_pred": 66353.0,
    "eth_pred": 1966.87
  },
  {
    "date": "2026-03-09",
    "btc_pred": 66263.47,
    "eth_pred": 1967.33
  },
  {
    "date": "2026-03-10",
    "btc_pred": 66173.94,
    "eth_pred": 1967.79
  },
  {
    "date": "2026-03-11",
    "btc_pred": 66084.41,
    "eth_pred": 1968.25
  },
  {
    "date": "2026-03-12",
    "btc_pred": 65994.88,
    "eth_pred": 1968.71
  },
  {
    "date": "2026-03-13",
    "btc_pred": 65905.35,
    "eth_pred": 1969.17
  },
  {
    "date": "2026-03-14",
    "btc_pred": 65815.82,
    "eth_pred": 1969.63
  },
  {
    "date": "2026-03-15",
    "btc_pred": 65726.3,
    "eth_pred": 1970.09
  },
  {
    "date": "2026-03-16",
    "btc_pred": 65636.77,
    "eth_pred": 1970.55
  },
  {
    "date": "2026-03-17",
    "btc_pred": 65547.24,
    "eth_pred": 1971.01
  },
  {
    "date": "2026-03-18",
    "btc_pred": 65457.71,
    "eth_pred": 1971.47
  },
  {
    "date": "2026-03-19",
    "btc_pred": 65368.18,
    "eth_pred": 1971.94
  },
  {
    "date": "2026-03-20",
    "btc_pred": 65278.65,
    "eth_pred": 1972.4
  },
  {
    "date": "2026-03-21",
    "btc_pred": 65189.12,
    "eth_pred": 1972.86
  },
  {
    "date": "2026-03-22",
    "btc_pred": 65099.59,
    "eth_pred": 1973.32
  }
]